akari_client/__init__.py
akari_client/akari_client.py
akari_client/color.py
akari_client/config.py
akari_client/joint_controller.py
akari_client/joint_manager.py
akari_client/m5stack_client.py
akari_client/position.py
akari_client/py.typed
akari_client/grpc/__init__.py
akari_client/grpc/_error.py
akari_client/grpc/channel_pool.py
akari_client/grpc/factory.py
akari_client/grpc/joints_controller.py
akari_client/grpc/m5stack.py
akari_client/serial/__init__.py
akari_client/serial/dynamixel.py
akari_client/serial/dynamixel_communicator.py
akari_client/serial/factory.py
akari_client/serial/feetech.py
akari_client/serial/feetech_communicator.py
akari_client/serial/m5stack.py
akari_client/serial/m5stack_communicator.py
akari_client-0.4.3.dist-info/METADATA
akari_client-0.4.3.dist-info/WHEEL
akari_client-0.4.3.dist-info/top_level.txt
akari_client-0.4.3.dist-info/RECORD
